arcpaykit/__init__.py
arcpaykit/client.py
arcpaykit/payments.py
arcpaykit-0.2.0.dist-info/licenses/LICENSE
arcpaykit-0.2.0.dist-info/METADATA
arcpaykit-0.2.0.dist-info/WHEEL
arcpaykit-0.2.0.dist-info/top_level.txt
arcpaykit-0.2.0.dist-info/RECORD
