Metadata-Version: 2.4
Name: arcpaykit
Version: 0.2.0
Summary: Official ArcPay Python SDK for accepting stablecoin payments
Home-page: https://github.com/arcpay/gateway
Author: ArcPay
Author-email: ArcPay <support@arcpaykit.com>
License: MIT
Project-URL: Documentation, https://docs.arcpaykit.com
Project-URL: Source, https://github.com/arcpay/gateway
Project-URL: Tracker, https://github.com/arcpay/gateway/issues
Keywords: payments,web3,stablecoin,arcpay,blockchain,cryptocurrency
Classifier: Development Status :: 4 - Beta
Classifier: Intended Audience :: Developers
Classifier: License :: OSI Approved :: MIT License
Classifier: Programming Language :: Python :: 3
Classifier: Programming Language :: Python :: 3.7
Classifier: Programming Language :: Python :: 3.8
Classifier: Programming Language :: Python :: 3.9
Classifier: Programming Language :: Python :: 3.10
Classifier: Programming Language :: Python :: 3.11
Classifier: Programming Language :: Python :: 3.12
Classifier: Topic :: Software Development :: Libraries :: Python Modules
Classifier: Topic :: Office/Business :: Financial
Requires-Python: >=3.7
License-File: LICENSE
Requires-Dist: requests>=2.31.0
Dynamic: author
Dynamic: home-page
Dynamic: license-file
Dynamic: requires-python
